mcp_http_tool/__init__.py
mcp_http_tool/__main__.py
mcp_http_tool-0.1.1.dist-info/licenses/LICENSE
mcp_http_tool-0.1.1.dist-info/METADATA
mcp_http_tool-0.1.1.dist-info/WHEEL
mcp_http_tool-0.1.1.dist-info/entry_points.txt
mcp_http_tool-0.1.1.dist-info/top_level.txt
mcp_http_tool-0.1.1.dist-info/RECORD
