Metadata-Version: 2.4
Name: mcp-http-tool
Version: 0.1.1
Summary: An MCP server that provides AI with robust HTTP request capabilities.
Author-email: mrbeandev <mrbeandev@gmail.com>
Classifier: Programming Language :: Python :: 3
Classifier: License :: OSI Approved :: MIT License
Classifier: Operating System :: OS Independent
Requires-Python: >=3.10
License-File: LICENSE
Requires-Dist: mcp[cli]
Requires-Dist: httpx>=0.24.0
Dynamic: license-file
